{
    "boards": {
        "c": 4,
        "cm": 15,
        "cgl": 8,
        "d": 5,
        "e": 4,
        "g": 10,
        "h": 15,
        "i": 5,
        "ic": 10,
        "mlp": 23,
        "qa": 8,
        "s4s": 3,
        "t": 16,
        "tg": 10,
        "vr": 10,
        "w": 4,
        "wg": 4,
        "y": 15
    },
    "files": {
        "c": 4,
        "cm": 15,
        "cgl": 8,
        "d": 5,
        "e": 4,
        "g": 8,
        "h": 15,
        "i": 5,
        "ic": 10,
        "qa": 8,
        "s4s": 3,
        "t": 16,
        "tg": 10,
        "vr": 10,
        "w": 4,
        "wg": 4,
        "y": 15
    }
}
